lunRNG.py
lunRNG-1.0.dist-info/LICENSE
lunRNG-1.0.dist-info/METADATA
lunRNG-1.0.dist-info/WHEEL
lunRNG-1.0.dist-info/top_level.txt
lunRNG-1.0.dist-info/RECORD
