Metadata-Version: 2.1
Name: lunRNG
Version: 1.0
Summary: random library using the moon as the seed
Author: snailBoy
Project-URL: Homepage, https://github.com/sna1lBoy/lunRNG
Project-URL: Issues, https://www.nasa.gov/
Classifier: Programming Language :: Python :: 3
Classifier: License :: OSI Approved :: GNU General Public License v3 (GPLv3)
Classifier: Operating System :: OS Independent
Requires-Python: >=3.11
License-File: LICENSE
Requires-Dist: pylunar
